pandas_mcp_server/__init__.py
pandas_mcp_server/cli.py
pandas_mcp_server/server.py
pandas_mcp_server_unofficial-0.1.0.dist-info/METADATA
pandas_mcp_server_unofficial-0.1.0.dist-info/WHEEL
pandas_mcp_server_unofficial-0.1.0.dist-info/entry_points.txt
pandas_mcp_server_unofficial-0.1.0.dist-info/top_level.txt
pandas_mcp_server_unofficial-0.1.0.dist-info/RECORD
