Metadata-Version: 2.4
Name: pandas-mcp-server-unofficial
Version: 0.1.0
Summary: An unofficial, packaged release of Marlon Luo's pandas-mcp-server for easy installation.
Author-email: Marlon Luo <marlonluo2018@gmail.com>
Maintainer-email: Peter Kuik <peter_kuik@epam.com>
License-Expression: MIT
Classifier: Programming Language :: Python :: 3
Classifier: Operating System :: OS Independent
Requires-Python: >=3.8
Requires-Dist: pandas>=1.0.0
